CHANGES.txt
LICENSE.txt
MANIFEST.in
README.txt
setup.py
src/p01/__init__.py
src/p01.elasticstub.egg-info/PKG-INFO
src/p01.elasticstub.egg-info/SOURCES.txt
src/p01.elasticstub.egg-info/dependency_links.txt
src/p01.elasticstub.egg-info/namespace_packages.txt
src/p01.elasticstub.egg-info/not-zip-safe
src/p01.elasticstub.egg-info/requires.txt
src/p01.elasticstub.egg-info/top_level.txt
src/p01/elasticstub/README.txt
src/p01/elasticstub/__init__.py
src/p01/elasticstub/testing.py
src/p01/elasticstub/config/elasticsearch.yml
src/p01/elasticstub/sandbox/LICENSE.txt
src/p01/elasticstub/sandbox/NOTICE.txt
src/p01/elasticstub/sandbox/config/elasticsearch.yml
src/p01/elasticstub/tests/__init__.py
src/p01/elasticstub/tests/test_parseconf.py
src/p01/elasticstub/tests/tests.py
src/p01/elasticstub/tests/config_empty/elasticsearch.yml
src/p01/elasticstub/tests/config_json/elasticsearch.json
src/p01/elasticstub/tests/config_yaml/elasticsearch.yml